dosei_sdk/__init__.py
dosei_sdk/app.py
dosei_sdk/importer.py
dosei_sdk/main.py
dosei_sdk/schemas/cron_jobs.py
dosei_sdk-0.0.20.dist-info/LICENSE
dosei_sdk-0.0.20.dist-info/METADATA
dosei_sdk-0.0.20.dist-info/WHEEL
dosei_sdk-0.0.20.dist-info/RECORD
