Metadata-Version: 2.1
Name: dosei-sdk
Version: 0.0.20
Summary: Dosei Python SDK
License: Apache-2.0
Author: Alvaro Molina
Author-email: am@dosei.ai
Requires-Python: >=3.11,<4.0
Classifier: License :: OSI Approved :: Apache Software License
Classifier: Programming Language :: Python :: 3
Classifier: Programming Language :: Python :: 3.11
Classifier: Programming Language :: Python :: 3.12
Requires-Dist: croniter (>=2.0.1,<3.0.0)
Requires-Dist: pydantic (>=2.6.1,<3.0.0)
